{"v":4,"entries":{"example-view2d--primary":{"type":"story","id":"example-view2d--primary","name":"Primary","title":"Example/View2d","importPath":"./src/stories/View2d.stories.tsx","tags":["story"]},"example-view2d--shapes":{"type":"story","id":"example-view2d--shapes","name":"Shapes","title":"Example/View2d","importPath":"./src/stories/View2d.stories.tsx","tags":["story"]},"example-view2d--mouse-position":{"type":"story","id":"example-view2d--mouse-position","name":"Mouse Position","title":"Example/View2d","importPath":"./src/stories/View2d.stories.tsx","tags":["story"]}}}
